Workbook

Sheet Práctica1
B2: Miércoles
B3: Ofimática
B4: Electricidad Uno

Sheet Práctica2
B4: HORARIO | C4: LUNES | D4: MARTES | E4: MIERCOLES | F4: JUEVES | G4: VIERNES
B5: 6:00 AM a 07:00 AM | D5: Dibujo en Ingenieria | E5: Dibujo en ingeniera | F5: Dibujo en Ingenieria | G5: Dibujo en Ingenieria
B6: 07:00 AM a 08:00 AM | E6: Habilidades SocAft | F6: Habilidades SocAft
B7: 08:00 AM a 09:00 AM
B8: 09:00 AM a 10:00 AM
B9: 10:00 AM a 11:00 AM | C9: Seminario de TE | G9: Seminario de TE
B10: 11:00 AM a 12:00 PM | C10: Seminario de E&L | E10: Seminario de E&L | F10: Seminario de E&L
B11: 12:00 PM a 01:00 PM
B12: 01:00 PM a 02:00 PM | E12: Ofimática P. | F12: Ofimática P. | G12: Ofimática P.
B13: 02:00 PM a 03:00 PM

Sheet Práctica 3
A1: Nombre | B1: Encargo | C1: Presupuesto
A2: Gualberto | B2: Almacenista | C2: 5000
A3: Alex | B3: Botarguero | C3: 1000
A4: Brandon | B4: Gerente | C4: 10000
A5: Oscar | B5: Dueño | C5: 20000

Sheet Práctica 4
C4: Nombre del componente | D4: Descripción del componenete | E4: Cantidad a comprar | F4: Costo Unitario | G4: Costo total | H4: Link del producto
C5: Resistencia 220 | D5: Limita el flujo de corriente eléctrica; comúnmente usada para proteger LEDs en circuitos de 5V | E5: 30 | F5: 0.5 | G5: =Tabla2[[#This Row],[Costo Unitario]]*Tabla2[[#This Row],[Cantidad a comprar]] -> 15
C6: Capacitor 47 Uf | D6: Almacena energía eléctrica temporalmente; utilizado para filtrado y estabilización de voltaje | E6: 15 | F6: 3 | G6: =Tabla2[[#This Row],[Costo Unitario]]*Tabla2[[#This Row],[Cantidad a comprar]] -> 45
C7: Potenciometro 10k | D7: Resistencia variable de 10 kiloohmios que permite ajustar manualmente niveles de voltaje o señal | E7: 15 | F7: 4.9 | G7: =Tabla2[[#This Row],[Costo Unitario]]*Tabla2[[#This Row],[Cantidad a comprar]] -> 73.5
C8: Diodos | D8: Componentes que permiten el flujo de corriente en una sola dirección, protegiendo contra polaridad inversa | E8: 10 | F8: 1.5 | G8: =Tabla2[[#This Row],[Costo Unitario]]*Tabla2[[#This Row],[Cantidad a comprar]] -> 15
C9: Led rojo | D9: Diodo emisor de luz de color rojo; utilizado como indicador visual de estado o funcionamiento | E9: 10 | F9: 2 | G9: =Tabla2[[#This Row],[Costo Unitario]]*Tabla2[[#This Row],[Cantidad a comprar]] -> 20
C10: Transistor bjt | D10: Dispositivo semiconductor utilizado para amplificar señales o como interruptor electrónico | E10: 15 | F10: 1.56 | G10: =Tabla2[[#This Row],[Costo Unitario]]*Tabla2[[#This Row],[Cantidad a comprar]] -> 23.4
C11: Opamp 741 | D11: Amplificador operacional clásico de un solo canal, utilizado en tareas generales de amplificación y comparación | E11: 5 | F11: 10.15 | G11: =Tabla2[[#This Row],[Costo Unitario]]*Tabla2[[#This Row],[Cantidad a comprar]] -> 50.75
C12: opamp lm324 | D12: Circuito integrado que contiene cuatro amplificadores operacionales independientes de bajo consumo | E12: 5 | F12: 7 | G12: =Tabla2[[#This Row],[Costo Unitario]]*Tabla2[[#This Row],[Cantidad a comprar]] -> 35
C13: Capacitor 1uf | D13: Componente para almacenamiento de carga; ideal para acoplamiento de señales y filtrado de alta frecuencia | E13: 10 | F13: 0.69 | G13: =Tabla2[[#This Row],[Costo Unitario]]*Tabla2[[#This Row],[Cantidad a comprar]] -> 6.9
C14: Regulador de voltaje LM7805 | D14: Regulador de voltaje lineal que proporciona una salida constante y estable de $+5$V | E14: 5 | F14: 8 | G14: =Tabla2[[#This Row],[Costo Unitario]]*Tabla2[[#This Row],[Cantidad a comprar]] -> 40
G15: =Tabla2[[#This Row],[Costo Unitario]]*Tabla2[[#This Row],[Cantidad a comprar]] -> 0

Sheet Práctica 5
A1: Calculadora de areas | E1: Decimal | F1: Binario | G1: HEX
A2: 5 | B2: 5 | C2: =A2*B2 -> 25 | E2: 14 | F2: =DEC2BIN(E2) -> 1110 | G2: =DEC2HEX(E2) -> E
A3: 2 | B3: 4 | C3: =A3*B3 -> 8 | E3: 4 | F3: =DEC2BIN(E3) -> 100 | G3: =DEC2HEX(E3) -> 4
A4: 3 | B4: 4 | C4: =A4*B4 -> 12 | E4: 24 | F4: =DEC2BIN(E4) -> 11000 | G4: =DEC2HEX(E4) -> 18
A5: 45 | B5: 9 | C5: =A5*B5 -> 405 | E5: 100 | F5: =DEC2BIN(E5) -> 1100100 | G5: =DEC2HEX(E5) -> 64
A6: 14 | B6: 6 | C6: =A6*B6 -> 84
A7: 57 | B7: 31 | C7: =A7*B7 -> 1767
A8: 6 | B8: 48 | C8: =A8*B8 -> 288 | E8: 2^5 | F8: 2^4 | G8: 2^3 | H8: 2^2 | I8: 2^1 | J8: 2^0
A9: 47 | B9: 5425 | C9: =A9*B9 -> 254975 | E9: 32 | F9: 16 | G9: 8 | H9: 4 | I9: 2 | J9: 1
A10: 222142 | B10: 525252 | C10: =A10*B10 -> 116680529784
A11: 5445 | B11: 787878 | C11: =A11*B11 -> 4289995710 | E11: Día | F11: Gasto | G11: Presupuesto
A12: 78 | B12: 32 | C12: =A12*B12 -> 2496 | E12: Lunes | F12: 150
A13: 789 | B13: 159 | C13: =A13*B13 -> 125451 | E13: Martes | F13: 341
A14: 12562 | B14: 125662 | C14: =A14*B14 -> 1578566044 | E14: Miércoles | F14: 124
A15: 741258 | B15: 25863.2 | C15: =A15*B15 -> 1.9171304e+10 | E15: Jueves | F15: 180
A16: 789621452 | B16: 520145201 | C16: =A16*B16 -> 4.1071781e+17 | E16: Viernes | F16: 500
A17: 45 | B17: 7896951 | C17: =A17*B17 -> 355362795 | E17: Total | F17: 1295 | G17: 3000
A18: 7888 | B18: 545454 | C18: =A18*B18 -> 4302541152 | E18: Estado
A19: 74 | B19: 5454 | C19: =A19*B19 -> 403596

Sheet Practica 6
A1: X | B1: Y | C1: Y2
A2: -5 | B2: =3*A2-2 -> -17 | C2: =A2*A2+1 -> 26 | D2: Y=3X-2
A3: -4 | B3: =3*A3-2 -> -14 | C3: =A3*A3+1 -> 17 | D3: Y2=A2*A2+1
A4: -3 | B4: =3*A4-2 -> -11 | C4: =A4*A4+1 -> 10
A5: -2 | B5: =3*A5-2 -> -8 | C5: =A5*A5+1 -> 5
A6: -1 | B6: =3*A6-2 -> -5 | C6: =A6*A6+1 -> 2
A7: 0 | B7: =3*A7-2 -> -2 | C7: =A7*A7+1 -> 1
A8: 1 | B8: =3*A8-2 -> 1 | C8: =A8*A8+1 -> 2
A9: 2 | B9: =3*A9-2 -> 4 | C9: =A9*A9+1 -> 5
A10: 3 | B10: =3*A10-2 -> 7 | C10: =A10*A10+1 -> 10
A11: 4 | B11: =3*A11-2 -> 10 | C11: =A11*A11+1 -> 17
A12: 5 | B12: =3*A12-2 -> 13 | C12: =A12*A12+1 -> 26
A16: EDADES | B16: PERSONAS | C16: PORCENTAJE
A17: 13-19 | B17: 12 | C17: =B17*100/217 -> 5.5299539
A18: 15-18 | B18: 63 | C18: =B18*100/217 -> 29.032258
A19: 18-21 | B19: 45 | C19: =B19*100/217 -> 20.737327
A20: 21-30 | B20: 97 | C20: =B20*100/217 -> 44.700461
B21: =SUM(B17:B20) -> 217 | C21: =B21*100/217 -> 100

Sheet Practica 7
A1: Rango de edad | B1: Num. De personas | C1: % de personas
A2: 17 | B2: 6 | C2: =B2*100/35 -> 17.142857
A3: 18 | B3: 17 | C3: =B3*100/35 -> 48.571429
A4: 19 | B4: 8 | C4: =B4*100/35 -> 22.857143
A5: 20 | B5: 3 | C5: =B5*100/35 -> 8.5714286
A6: 21 | B6: 1 | C6: =B6*100/35 -> 2.8571429
A7: TOTAL | B7: =SUM(B2:B6) -> 35 | C7: =B7*100/35 -> 100

Sheet Practica8
A1: Tiempo (s) | B1: Voltaje con Ruido (V) | E1: Tiempo (s) | F1: Voltaje Ideal | L1: Tiempo (s) | M1: Voltaje Ideal | S1: Tiempo (s) | T1: Voltaje Ideal | Z1: Tiempo (s) | AA1: Voltaje Ideal | AF1: Tiempo (s) | AG1: Voltaje Ideal
A2: 0 | B2: 0.02 | E2: 0 | F2: =H$3*(1-EXP(-E2/I$3)) -> 0 | H2: Vfuente | I2: cte de tiempo | L2: 0 | M2: =O$3*(1-EXP(-L2/P$3)) -> 0 | O2: Vfuente | P2: cte de tiempo | S2: 0 | T2: =V$3*(1-EXP(-S2/W$3)) -> 0 | V2: Vfuente | W2: cte de tiempo | Z2: 0 | AA2: =AC$3*(1-EXP(-Z2/AD$3)) -> 0 | AC2: Vfuente | AD2: cte de tiempo | AF2: 0 | AG2: =AI$3*(1-EXP(-AF2/AJ$3)) -> 0 | AI2: Vfuente | AJ2: cte de tiempo
A3: 0.05 | B3: 0.22 | E3: 0.05 | F3: =H$3*(1-EXP(-E3/I$3)) -> 0.24385288 | H3: 5 | I3: 1 | L3: 0.05 | M3: =O$3*(1-EXP(-L3/P$3)) -> 0.049750831 | O3: 5 | P3: 5 | S3: 0.05 | T3: =V$3*(1-EXP(-S3/W$3)) -> 0.024937604 | V3: 5 | W3: 10 | Z3: 0.05 | AA3: =AC$3*(1-EXP(-Z3/AD$3)) -> 0.01663892 | AC3: 5 | AD3: 15 | AF3: 0.05 | AG3: =AI$3*(1-EXP(-AF3/AJ$3)) -> 0.012484388 | AI3: 5 | AJ3: 20
A4: 0.1 | B4: 0.45 | E4: 0.1 | F4: =H$3*(1-EXP(-E4/I$3)) -> 0.47581291 | L4: 0.1 | M4: =O$3*(1-EXP(-L4/P$3)) -> 0.099006633 | S4: 0.1 | T4: =V$3*(1-EXP(-S4/W$3)) -> 0.049750831 | Z4: 0.1 | AA4: =AC$3*(1-EXP(-Z4/AD$3)) -> 0.033222469 | AF4: 0.1 | AG4: =AI$3*(1-EXP(-AF4/AJ$3)) -> 0.024937604
A5: 0.15 | B5: 0.63 | E5: 0.15 | F5: =H$3*(1-EXP(-E5/I$3)) -> 0.69646012 | L5: 0.15 | M5: =O$3*(1-EXP(-L5/P$3)) -> 0.14777233 | S5: 0.15 | T5: =V$3*(1-EXP(-S5/W$3)) -> 0.074440302 | Z5: 0.15 | AA5: =AC$3*(1-EXP(-Z5/AD$3)) -> 0.049750831 | AF5: 0.15 | AG5: =AI$3*(1-EXP(-AF5/AJ$3)) -> 0.037359726
A6: 0.2 | B6: 0.78 | E6: 0.2 | F6: =H$3*(1-EXP(-E6/I$3)) -> 0.90634623 | L6: 0.2 | M6: =O$3*(1-EXP(-L6/P$3)) -> 0.1960528 | S6: 0.2 | T6: =V$3*(1-EXP(-S6/W$3)) -> 0.099006633 | Z6: 0.2 | AA6: =AC$3*(1-EXP(-Z6/AD$3)) -> 0.066224191 | AF6: 0.2 | AG6: =AI$3*(1-EXP(-AF6/AJ$3)) -> 0.049750831
A7: 0.25 | B7: 0.92 | E7: 0.25 | F7: =H$3*(1-EXP(-E7/I$3)) -> 1.1059961 | L7: 0.25 | M7: =O$3*(1-EXP(-L7/P$3)) -> 0.24385288 | S7: 0.25 | T7: =V$3*(1-EXP(-S7/W$3)) -> 0.12345044 | Z7: 0.25 | AA7: =AC$3*(1-EXP(-Z7/AD$3)) -> 0.082642731 | AF7: 0.25 | AG7: =AI$3*(1-EXP(-AF7/AJ$3)) -> 0.062110998
A8: 0.3 | B8: 1.05 | E8: 0.3 | F8: =H$3*(1-EXP(-E8/I$3)) -> 1.2959089 | L8: 0.3 | M8: =O$3*(1-EXP(-L8/P$3)) -> 0.29117733 | S8: 0.3 | T8: =V$3*(1-EXP(-S8/W$3)) -> 0.14777233 | Z8: 0.3 | AA8: =AC$3*(1-EXP(-Z8/AD$3)) -> 0.099006633 | AF8: 0.3 | AG8: =AI$3*(1-EXP(-AF8/AJ$3)) -> 0.074440302
A9: 0.35 | B9: 1.18 | E9: 0.35 | F9: =H$3*(1-EXP(-E9/I$3)) -> 1.4765596 | L9: 0.35 | M9: =O$3*(1-EXP(-L9/P$3)) -> 0.3380309 | S9: 0.35 | T9: =V$3*(1-EXP(-S9/W$3)) -> 0.17197292 | Z9: 0.35 | AA9: =AC$3*(1-EXP(-Z9/AD$3)) -> 0.11531608 | AF9: 0.35 | AG9: =AI$3*(1-EXP(-AF9/AJ$3)) -> 0.086738822
A10: 0.4 | B10: 1.25 | E10: 0.4 | F10: =H$3*(1-EXP(-E10/I$3)) -> 1.6483998 | L10: 0.4 | M10: =O$3*(1-EXP(-L10/P$3)) -> 0.38441827 | S10: 0.4 | T10: =V$3*(1-EXP(-S10/W$3)) -> 0.1960528 | Z10: 0.4 | AA10: =AC$3*(1-EXP(-Z10/AD$3)) -> 0.13157125 | AF10: 0.4 | AG10: =AI$3*(1-EXP(-AF10/AJ$3)) -> 0.099006633
A11: 0.45 | B11: 1.38 | E11: 0.45 | F11: =H$3*(1-EXP(-E11/I$3)) -> 1.8118592 | L11: 0.45 | M11: =O$3*(1-EXP(-L11/P$3)) -> 0.43034407 | S11: 0.45 | T11: =V$3*(1-EXP(-S11/W$3)) -> 0.22001259 | Z11: 0.45 | AA11: =AC$3*(1-EXP(-Z11/AD$3)) -> 0.14777233 | AF11: 0.45 | AG11: =AI$3*(1-EXP(-AF11/AJ$3)) -> 0.11124381
A12: 0.5 | B12: 1.55 | E12: 0.5 | F12: =H$3*(1-EXP(-E12/I$3)) -> 1.9673467 | L12: 0.5 | M12: =O$3*(1-EXP(-L12/P$3)) -> 0.47581291 | S12: 0.5 | T12: =V$3*(1-EXP(-S12/W$3)) -> 0.24385288 | Z12: 0.5 | AA12: =AC$3*(1-EXP(-Z12/AD$3)) -> 0.1639195 | AF12: 0.5 | AG12: =AI$3*(1-EXP(-AF12/AJ$3)) -> 0.12345044
A13: 0.55 | B13: 1.62 | E13: 0.55 | F13: =H$3*(1-EXP(-E13/I$3)) -> 2.1152509 | L13: 0.55 | M13: =O$3*(1-EXP(-L13/P$3)) -> 0.52082932 | S13: 0.55 | T13: =V$3*(1-EXP(-S13/W$3)) -> 0.26757426 | Z13: 0.55 | AA13: =AC$3*(1-EXP(-Z13/AD$3)) -> 0.18001293 | AF13: 0.55 | AG13: =AI$3*(1-EXP(-AF13/AJ$3)) -> 0.13562659
A14: 0.6 | B14: 1.8 | E14: 0.6 | F14: =H$3*(1-EXP(-E14/I$3)) -> 2.2559418 | L14: 0.6 | M14: =O$3*(1-EXP(-L14/P$3)) -> 0.56539782 | S14: 0.6 | T14: =V$3*(1-EXP(-S14/W$3)) -> 0.29117733 | Z14: 0.6 | AA14: =AC$3*(1-EXP(-Z14/AD$3)) -> 0.1960528 | AF14: 0.6 | AG14: =AI$3*(1-EXP(-AF14/AJ$3)) -> 0.14777233
A15: 0.65 | B15: 1.88 | E15: 0.65 | F15: =H$3*(1-EXP(-E15/I$3)) -> 2.3897711 | L15: 0.65 | M15: =O$3*(1-EXP(-L15/P$3)) -> 0.60952285 | S15: 0.65 | T15: =V$3*(1-EXP(-S15/W$3)) -> 0.31466268 | Z15: 0.65 | AA15: =AC$3*(1-EXP(-Z15/AD$3)) -> 0.2120393 | AF15: 0.65 | AG15: =AI$3*(1-EXP(-AF15/AJ$3)) -> 0.15988775
... A45: 10 | B45: 4.98 | E45: 10 | F45: =H$3*(1-EXP(-E45/I$3)) -> 4.999773 | L45: 10 | M45: =O$3*(1-EXP(-L45/P$3)) -> 4.3233236 | S45: 10 | T45: =V$3*(1-EXP(-S45/W$3)) -> 3.1606028 | Z45: 10 | AA45: =AC$3*(1-EXP(-Z45/AD$3)) -> 2.4329144 | AF45: 10 | AG45: =AI$3*(1-EXP(-AF45/AJ$3)) -> 1.9673467

Sheet Práctica 9
A1: Nombre | B1: Edad | C1: Sexo | D1: Grado | E1: Calificación | F1: Tipo de Evaluacion
A2: Emmanuel Rodriguez | B2: 16 | C2: m | D2: 1 | E2: 9 | F2: extra
A3: Jonatan Vazquez | B3: 17 | C3: m | D3: 2 | E3: 7 | F3: ordi
A4: Abraham Gaytan | B4: 20 | C4: m | D4: 9 | E4: 8 | F4: ordi
A5: Poala Linderos | B5: 16 | C5: f | D5: 1 | E5: 8 | F5: extra
A6: Alejandra Bautisa | B6: 20 | C6: f | D6: 3 | E6: 8 | F6: extra
A7: Adolfo Ferruzca | B7: 18 | C7: m | D7: 2 | E7: 7 | F7: ordi
A8: Rolando Campos | B8: 18 | C8: m | D8: 3 | E8: 6 | F8: ordi
A9: Daniela Peña | B9: 16 | C9: f | D9: 1 | E9: 7 | F9: extra
B11: Edad | C11: Sexo | D11: Grado | E11: Calificación | F11: Tipo de Evaluacion
B12: 16 | C12: m | D12: 2 | E12: 6 | F12: ordi
A13: BDCONTAR | B13: =DCOUNT(A1:F9, "Edad", B11:B12) -> 3 | C13: =DCOUNT(A1:F9,"Sexo",C11:C12) -> 0 | D13: =DCOUNT(A1:F9,"Grado",D11:D12) -> 2 | E13: =DCOUNT(A1:F9,"Calificación", E11:E12) -> 1 | F13: =DCOUNT(A1:F9,"Tipo de Evaluacion",F11:F12) -> 0
A14: BDCONTARA | B14: =DCOUNTA(A1:F9,"Edad",B11:B12) -> 3 | C14: =DCOUNTA(A1:F9,"Sexo",C11:C12) -> 5 | D14: =DCOUNTA(A1:F9,"Grado",D11:D12) -> 2 | E14: =DCOUNTA(A1:F9,"Calificación", E11:E12) -> 1 | F14: =DCOUNTA(A1:F9,"Tipo de Evaluacion",F11:F12) -> 4
A15: BDMAX | B15: =DMAX(A1:F9,"Edad",B11:B12) -> 16 | C15: =DMAX(A1:F9,"Sexo",C11:C12) -> 0 | D15: =DMAX(A1:F9,"Grado",D11:D12) -> 2 | E15: =DMAX(A1:F9,"Calificación", E11:E12) -> 6 | F15: =DMAX(A1:F9,"Tipo de Evaluacion",F11:F12) -> 0
A16: BDMIN | B16: =DMIN(A1:F9,"Edad",B11:B12) -> 16 | C16: =DMIN(A1:F9,"Sexo",C11:C12) -> 0 | D16: =DMIN(A1:F9,"Grado",D11:D12) -> 2 | E16: =DMIN(A1:F9,"Calificación", E11:E12) -> 6 | F16: =DMIN(A1:F9,"Tipo de Evaluacion",F11:F12) -> 0
A17: BDSUMA | B17: =DSUM(A1:F9,"Edad",B11:B12) -> 48 | C17: =DSUM(A1:F9,"Sexo",C11:C12) -> 0 | D17: =DSUM(A1:F9,"Grado",D11:D12) -> 4 | E17: =DAVERAGE(A1:F9,"Calificación", E11:E12) -> 6 | F17: =DSUM(A1:F9,"Tipo de Evaluacion",F11:F12) -> 0
A18: BDPROMEDIO | B18: =DAVERAGE(A1:F9, "Edad",B11:B12) -> 16 | C18: =DAVERAGE(A1:F9,"Sexo",C11:C12) -> #DIV/0! | D18: =DAVERAGE(A1:F9,"Grado",D11:D12) -> 2 | E18: =DSUM(A1:F9,"Calificación", E11:E12) -> 6 | F18: =DAVERAGE(A1:F9,"Tipo de Evaluacion",F11:F12) -> #DIV/0!
A19: BDPRODUCTO | B19: =DPRODUCT(A1:F9,"Edad",B11:B12) -> 4096 | C19: =DPRODUCT(A1:F9,"Sexo",C11:C12) -> 0 | D19: =DPRODUCT(A1:F9,"Grado",D11:D12) -> 4 | E19: =DPRODUCT(A1:F9,"Calificación", E11:E12) -> 6 | F19: =DPRODUCT(A1:F9,"Tipo de Evaluacion",F11:F12) -> 0

Sheet Practica 10
A1: Nombre | B1: Apellidos | C1: Clase | D1: Lenguaje | E1: Matemáticas | F1: História | G1: Media | H1: NotLenguaje | I1: NotMat | J1: NotHis
A2: Txetxu | B2: Arazabaleta | C2: A | D2: 5 | E2: 7 | F2: 9 | G2: A | H2: Reprobado | I2: Aprobado | J2: Aprobado | N2: Notas
A3: Itziar | B3: Bengoetxea | C3: B | D3: 7 | E3: 5 | F3: 5 | G3: 5.6666667 | H3: Aprobado | I3: Reprobado | J3: Reprobado | O3: Suspendidos | P3: Aprobados
A4: Prudencia | B4: Gara | C4: C | D4: 3 | E4: 8 | F4: 5 | G4: 5.3333333 | H4: Reprobado | I4: Aprobado | J4: Reprobado | N4: Lenguaje | O4: 7 | P4: 15
A5: Leocadia | B5: Garcia | C5: B | D5: 6 | E5: 5 | F5: 8 | G5: 6.3333333 | H5: Aprobado | I5: Reprobado | J5: Aprobado | N5: Matemáticas | O5: 11 | P5: 11
A6: Estrellita | B6: Gutierrez | C6: C | D6: 6 | E6: 6 | F6: 7 | G6: 6.3333333 | H6: Aprobado | I6: Aprobado | J6: Aprobado | N6: Historia | O6: 7 | P6: 15
A7: Romualdo | B7: Gutierrez | C7: B | D7: 8 | E7: 4 | F7: 6 | G7: 6 | H7: Aprobado | I7: Reprobado | J7: Aprobado
A8: Godofredo | B8: Martineti | C8: A | D8: 7 | E8: 5 | F8: 6 | G8: 6 | H8: Aprobado | I8: Reprobado | J8: Aprobado
A9: Sigfrido | B9: Martinez | C9: C | D9: 5 | E9: 7 | F9: 8 | G9: 6.6666667 | H9: Reprobado | I9: Aprobado | J9: Aprobado | M9: Nota Máxim por clase y asignatura
A10: Gumersindo | B10: Martinez | C10: C | D10: 7 | E10: 6 | F10: 5 | G10: 6 | H10: Aprobado | I10: Aprobado | J10: Reprobado | N10: Clase A | O10: Claase B | P10: Clase C
A11: Leovigildo | B11: Mastuerzo | C11: B | D11: 8 | E11: 9 | F11: 8 | G11: 8.3333333 | H11: Aprobado | I11: Aprobado | J11: Aprobado | M11: Lenguaje | N11: 8 | O11: 9 | P11: 7
A12: Heladio | B12: Parralo | C12: A | D12: 6 | E12: 3 | F12: 9 | G12: 6 | H12: Aprobado | I12: Reprobado | J12: Aprobado | M12: Matemáticas | N12: 7 | O12: 9 | P12: 8
A13: Urko | B13: Perez | C13: A | D13: 7 | E13: 4 | F13: 5 | G13: 5.3333333 | H13: Aprobado | I13: Reprobado | J13: Reprobado | M13: Historia | N13: 9 | O13: 8 | P13: 8
A14: Higinia | B14: Perez | C14: A | D14: 3 | E14: 4 | F14: 7 | G14: 4.6666667 | H14: Reprobado | I14: Reprobado | J14: Aprobado
A15: Teodófilo | B15: Peritarpei | C15: A | D15: 6 | E15: 3 | F15: 9 | G15: 6 | H15: Aprobado | I15: Reprobado | J15: Aprobado
A16: Macarena | B16: Pitu | C16: B | D16: 6 | E16: 5 | F16: 6 | G16: 5.6666667 | H16: Aprobado | I16: Reprobado | J16: Aprobado
A17: Quintiliano | B17: Sanchez | C17: C | D17: 3 | E17: 8 | F17: 5 | G17: 5.3333333 | H17: Reprobado | I17: Aprobado | J17: Reprobado | M17: Media por Clase y Asignatura
A18: Romualdo | B18: Santemesma | C18: B | D18: 9 | E18: 3 | F18: 7 | G18: 6.3333333 | H18: Aprobado | I18: Reprobado | J18: Aprobado | N18: Clase A | O18: Claase B | P18: Clase C
A19: Ataulfo | B19: Segarra | C19: A | D19: 5 | E19: 5 | F19: 6 | G19: 5.3333333 | H19: Reprobado | I19: Reprobado | J19: Aprobado | M19: Lenguaje | N19: =AVERAGEIF($C$2:$C$23,"A",$D$2:$D$23) -> 5.875 | O19: =AVERAGEIF($C$2:$C$23, "B", $D$2:$D$23) -> 7.4285714 | P19: =AVERAGEIF($C$2:$C$23, "C", $D$2:$D$23) -> 5
A20: Demetrio | B20: Sinforoso | C20: C | D20: 7 | E20: 7 | F20: 3 | G20: 5.6666667 | H20: Aprobado | I20: Aprobado | J20: Reprobado | M20: Matemáticas | N20: =AVERAGEIF($C$2:$C$23, "A", $E$2:$E$23) -> 4.75 | O20: =AVERAGEIF($C$2:$C$23, "B", $E$2:$E$23) -> 5.2857143 | P20: =AVERAGEIF($C$2:$C$23, "C", $E$2:$E$23) -> 6.8571429
A21: Abunciana | B21: Torrelles | C21: A | D21: 8 | E21: 7 | F21: 3 | G21: 6 | H21: Aprobado | I21: Aprobado | J21: Reprobado | M21: Historia | N21: =AVERAGEIF($C$2:$C$23, "A", $F$2:$F$23) -> 6.75 | O21: =AVERAGEIF($C$2:$C$23, "B", $F$2:$F$23) -> 6.7142857 | P21: =AVERAGEIF($C$2:$C$23, "C", $F$2:$F$23) -> 5.8571429
A22: Hugo | B22: Urdiales | C22: B | D22: 8 | E22: 6 | F22: 7 | G22: 7 | H22: Aprobado | I22: Aprobado | J22: Aprobado
A23: Idoia | B23: Zumalacarregui | C23: C | D23: 4 | E23: 6 | F23: 8 | G23: 6 | H23: Reprobado | I23: Aprobado | J23: Aprobado
A24: total de examenes | D24: 22 | E24: 22 | F24: 22
A25: Media | D25: 6.0909091 | E25: 5.5909091 | F25: 6.4545455
A26: Moda | D26: 7 | E26: 5 | F26: 5

Sheet Practica11_5
A1: TABLA
A2: 1 | B2: 100 | C2: Oscar | D2: 1 | E2: 100 | G2: Sueldo | H2: 1200
A3: 101 | B3: 500 | C3: Jose | D3: 101 | E3: 500 | G3: Porcentaje | H3: =VLOOKUP(H2,A2:C6,2,TRUE) -> 1500
A4: 501 | B4: 1000 | C4: Juan | D4: 501 | E4: 1000 | G4: Trabajador | H4: =VLOOKUP(H2,A2:C6,3,TRUE) -> Rodolfo
A5: 1001 | B5: 1500 | C5: Rodolfo | D5: 1001 | E5: 1500
A6: 1501 | C6: Julio | D6: 1501

Sheet Practica6
A1: CODIGO | B1: 100 | C1: 101 | D1: 102 | E1: 103 | F1: 104 | G1: 105 | H1: 106 | I1: 107
A2: ARTICULO | B2: TELEVISOR | C2: RADIO | D2: ORDENADOR | E2: IMPRESORA | F2: VIDEO | G2: CAMARA | H2: RELOJ | I2: TELEFONO
A3: MARCA | B3: ELBE | C3: SONY | D3: IBM | E3: EPSON | F3: SONY | G3: SABA | H3: ROLEX | I3: AIRTEL
A4: PRECIO | B4: 80000 | C4: 12000 | D4: 200000 | E4: 50000 | F4: 75000 | G4: 125000 | H4: 5000 | I4: 10000
A7: CODIGO | B7: ARTICULO | C7: MARCA | D7: PRECIO
A8: 102 | B8: =HLOOKUP(A8,$B$1:$I$4,2,FALSE) -> ORDENADOR | C8: =HLOOKUP(A8,B1:I4,3,FALSE) -> IBM | D8: =HLOOKUP(A8,B1:I4,4,FALSE) -> 200000
A9: 100 | B9: =HLOOKUP(A9,B1:I4,2,FALSE) -> TELEVISOR | C9: =HLOOKUP(A9,B1:I4,3,FALSE) -> ELBE | D9: =HLOOKUP(A9,B1:I4,4,FALSE) -> 80000
A14: CODIGO | B14: ARTICULO | C14: MARCA | D14: PRECIO
A15: 100 | B15: TELEVISOR | C15: ELBE | D15: 80000
A16: 101 | B16: RADIO | C16: SONY | D16: 12000
A17: 102 | B17: ORDENADOR | C17: IBM | D17: 200000
A18: 103 | B18: IMPRESORA | C18: EPSON | D18: 50000
A19: 104 | B19: VIDEO | C19: SONY | D19: 75000
A20: 105 | B20: CAMARA | C20: SABA | D20: 125000
A21: 106 | B21: RELOJ | C21: ROLEX | D21: 5000
A22: 107 | B22: TELEFONO | C22: AIRTEL | D22: 10000

Sheet Practica7
B7: INVOICE
B8: COMPANY ADRESS
A9: NAME | B9: LOKOTEL
A10: ADDRESS | B10: LOS NARANJOS 437
A11: STATE | B11: EBANO
A12: TYPE
A14: ITEM NUMBER | B14: DESCRPTION | C14: UNIT PRICE | D14: QUANTITY | E14: EXTENDED PRICE
A15: 1 | B15: =IF(A15="","",HLOOKUP(A15,Practica7_1!$A$1:$L$3,2,FALSE)) -> 1.2GB HARD DISK | C15: =IF(A15="","",HLOOKUP(A15,Practica7_1!$A$1:$L$3,3,FALSE)) -> 245.95 | D15: 5 | E15: =C15*D15 -> 1229.75
A16: 2 | B16: =IF(A16="","",HLOOKUP(A16,Practica7_1!$A$1:$L$3,2,FALSE)) -> 850MB HARD DISK | C16: =IF(A16="","",HLOOKUP(A16,Practica7_1!$A$1:$L$3,3,FALSE)) -> 145.95 | D16: 3 | E16: =C16*D16 -> 437.85
A17: 7 | B17: =IF(A17="","",HLOOKUP(A17,Practica7_1!$A$1:$L$3,2,FALSE)) -> 101 KEYBOARD | C17: =IF(A17="","",HLOOKUP(A17,Practica7_1!$A$1:$L$3,3,FALSE)) -> 45.95 | D17: 2 | E17: =C17*D17 -> 91.9
A18: 9 | B18: =IF(A18="","",HLOOKUP(A18,Practica7_1!$A$1:$L$3,2,FALSE)) -> LASER PRINTER | C18: =IF(A18="","",HLOOKUP(A18,Practica7_1!$A$1:$L$3,3,FALSE)) -> 76.98 | D18: 1 | E18: =C18*D18 -> 76.98
A19: 5 | B19: =IF(A19="","",HLOOKUP(A19,Practica7_1!$A$1:$L$3,2,FALSE)) -> SVGA MONITOR | C19: =IF(A19="","",HLOOKUP(A19,Practica7_1!$A$1:$L$3,3,FALSE)) -> 289.99 | D19: 1 | E19: =C19*D19 -> 289.99
B20: =IF(A20="","",HLOOKUP(A20,Practica7_1!$A$1:$L$3,2,FALSE)) | C20: =IF(A20="","",HLOOKUP(A20,Practica7_1!$A$1:$L$3,3,FALSE))
B21: =IF(A21="","",HLOOKUP(A21,Practica7_1!$A$1:$L$3,2,FALSE)) | C21: =IF(A21="","",HLOOKUP(A21,Practica7_1!$A$1:$L$3,3,FALSE))
B22: =IF(A22="","",HLOOKUP(A22,Practica7_1!$A$1:$L$3,2,FALSE)) | C22: =IF(A22="","",HLOOKUP(A22,Practica7_1!$A$1:$L$3,3,FALSE))
C23: =IF(A23="","",HLOOKUP(A23,Practica7_1!$A$1:$L$3,3,FALSE))
C24: =IF(A24="","",HLOOKUP(A24,Practica7_1!$A$1:$L$3,3,FALSE))
C25: =IF(A25="","",HLOOKUP(A25,Practica7_1!$A$1:$L$3,3,FALSE))
D26: SUBTOTAL | E26: =SUM(E15:E25) -> 2126.47
D27: DISCOUNT | E27: 0
D28: TAX | E28: =E26*(1-E27)*0.16 -> 340.2352
D29: FREIGHT | E29: 50
D30: TOTAL | E30: =E26*(1-E27)+E28+E29 -> 2516.7052
D31: COMMISION | E31: =E30*0.05 -> 125.83526

Sheet Practica7_1
A1: ITEM # | B1: 1 | C1: 2 | D1: 3 | E1: 4 | F1: 5 | G1: 6 | H1: 7 | I1: 8 | J1: 9 | K1: 10 | L1: 11
A2: DESCRIPTION | B2: 1.2GB HARD DISK | C2: 850MB HARD DISK | D2: 545MB HARDISK | E2: 1.44MB FLOPPY DISK | F2: SVGA MONITOR | G2: UVGA MONITOR | H2: 101 KEYBOARD | I2: DOT MATRIX PRINTER | J2: LASER PRINTER | K2: INK JET PRINTER | L2: INVALID
A3: UNIT PRICE | B3: 245.95 | C3: 145.95 | D3: 75.25 | E3: 25.95 | F3: 289.99 | G3: 345.25 | H3: 45.95 | I3: 123.96 | J3: 76.98 | K3: 245.55
